DCS_with_48_ClkCycles.v
module DCS(input clk, start ,crc, d,control,output [15:0] CRC_out,output  done_fec,output [23:0] outA , outB , outC , outD);
wire [95:0] fec_out;
wire mux_out;
CRC C(d , clk , start , CRC_out);
MUX M(control , d , crc , mux_out);
FEC F(mux_out, clk, start ,fec_out,done_fec);
Interleaver I(fec_out[95:88], fec_out[87:80] , fec_out[79:72] , fec_out[71:64] , fec_out[63:56] , fec_out[55:48] , fec_out[47:40] , fec_out[39:32] , fec_out[31:24] , fec_out[23:16] , fec_out[15:8] , fec_out[7:0], outA , outB , outC , outD);
endmodule

module CRC(input data , clk , start,output reg [15:0] r);
integer count;
always @(posedge clk , posedge start)
begin 
if(start)
begin
r = 16'hFFFF;
count = 32;
end
else if(count != 0)
begin
r[0] <=  data + r[15];
r[1] <=  r[0];
r[2] <= r[1] + (data + r[15]);
r[3] <= r[2];
r[4] <= r[3];
r[5] <= r[4];
r[6] <= r[5];
r[7] <= r[6];
r[8] <= r[7];
r[9] <= r[8];
r[10] <= r[9];
r[11] <= r[10];
r[12] <= r[11];
r[13] <= r[12];
r[14] <= r[13];
r[15] <= r[14]+(data+r[15]);
count <= count -1;
end
end
endmodule


module MUX(input control, d , crc ,output out);
assign out = (control && crc) || (~control && d);
endmodule

module FEC(input q,clk,reset,output reg [95:0] fec,output reg done);
reg [3:0] D;
integer count;
reg [47:0] P1,P0;
always @(posedge clk ,reset)
#1 begin
if(reset == 1)
begin
D <= 4'b0000;
count = 48;
done = 0;
end
else if(count >= 0)
begin
P0[count] = D[3]^D[2]^D[1]^D[0];
P1[count] = D[3]^D[1]^D[0];
fec = {fec[93:0],P1[count],P0[count]};
D = {q,D[3:1]};
if(count == 0)
done = 1;
else
begin
done = 0;
end
count =  count -1;
end
end
endmodule

module Interleaver(input [7:0] byte0, byte1, byte2, byte3, byte4, byte5, byte6, byte7, byte8, byte9, byte10, byte11,output [23:0] out0 , out1 , out2 , out3);
assign  out0 = { byte11[1:0],byte10[1:0] , byte9[1:0] , byte8[1:0] , byte7[1:0] , byte6[1:0] , byte5[1:0] , byte4[1:0] , byte3[1:0] , byte2[1:0] , byte1[1:0] , byte0[1:0]}; 
assign out1 = {byte11[3:2],byte10[3:2], byte9[3:2], byte8[3:2], byte7[3:2], byte6[3:2], byte5[3:2], byte4[3:2],byte3[3:2] , byte2[3:2] , byte1[3:2] , byte0[3:2]};
assign out2 = {byte11[5:4], byte10[5:4], byte9[5:4], byte8[5:4], byte7[5:4], byte6[5:4], byte5[5:4], byte4[5:4],byte3[5:4] , byte2[5:4] , byte1[5:4] , byte0[5:4]};
assign out3 = {byte11[7:6], byte10[7:6], byte9[7:6], byte8[7:6], byte7[7:6], byte6[7:6], byte5[7:6], byte4[7:6],byte3[7:6] , byte2[7:6] , byte1[7:6] , byte0[7:6]};
endmodule

testDCS.v
module test;
  reg clk , start ,d;
  wire[95:0] final_ans;
  wire  done;
  wire [15:0] CRC_out;
  
  
  
  reg [31:0] data = 32'h03_01_02_03;
  
  reg [47 :0] fec_in;
  
  DCS R(clk , start , d  , fec_in, CRC_out, done,final_ans);
  
  initial
    begin
      clk = 0;
      repeat(70)
        #5 clk = ~clk;
    end
  
  initial
    begin
      $dumpfile("dump.vcd");
      $dumpvars(1,test);
      $monitor($time , " final = %h done = %h",final_ans,done);
      
      start = 1;d = 0; 
      #5  start= 0;
      repeat(32)
        begin
          d = data[31];
          #10 data = data << 1; 
          fec_in = {32'h03_01_02_03 , CRC_out};
        end
      
      
      
     
      
    end
 
endmodule

dump.vcd
$date
	Wed Jun 16 08:30:38 2021
$end
$version
	Icarus Verilog
$end
$timescale
	1s
$end
$scope module test $end
$var wire 16 ! CRC_out [15:0] $end
$var wire 1 " done $end
$var wire 96 # final_ans [95:0] $end
$var reg 1 $ clk $end
$var reg 1 % d $end
$var reg 32 & data [31:0] $end
$var reg 48 ' fec_in [47:0] $end
$var reg 1 ( start $end
$upscope $end
$enddefinitions $end
#0
$dumpvars
1(
bx '
b11000000010000001000000011 &
0%
0$
bx #
x"
b1111111111111111 !
$end
#5
b111111111111011 !
0(
1$
#10
0$
#15
b1111111111110110 !
1$
b110000000100000010000000110111111111111011 '
b110000000100000010000000110 &
#20
0$
#25
b111111111101001 !
1$
b110000000100000010000000111111111111110110 '
b1100000001000000100000001100 &
#30
0$
#35
b1111111111010010 !
1$
b110000000100000010000000110111111111101001 '
b11000000010000001000000011000 &
#40
0$
#45
b111111110100001 !
1$
b110000000100000010000000111111111111010010 '
b110000000100000010000000110000 &
#50
0$
#55
b1111111101000010 !
1$
b110000000100000010000000110111111110100001 '
b1100000001000000100000001100000 &
#60
0$
#65
b1111111010000100 !
1$
1%
b110000000100000010000000111111111101000010 '
b11000000010000001000000011000000 &
#70
0$
#75
b1111110100001000 !
1$
b110000000100000010000000111111111010000100 '
b10000000100000010000000110000000 &
#80
0$
#85
b111101000010101 !
1$
0%
b110000000100000010000000111111110100001000 '
b1000000100000001100000000 &
#90
0$
#95
b1111010000101010 !
1$
b110000000100000010000000110111101000010101 '
b10000001000000011000000000 &
#100
0$
#105
b110100001010001 !
1$
b110000000100000010000000111111010000101010 '
b100000010000000110000000000 &
#110
0$
#115
b1101000010100010 !
1$
b110000000100000010000000110110100001010001 '
b1000000100000001100000000000 &
#120
0$
#125
b10000101000001 !
1$
b110000000100000010000000111101000010100010 '
b10000001000000011000000000000 &
#130
0$
#135
b100001010000010 !
1$
b110000000100000010000000110010000101000001 '
b100000010000000110000000000000 &
#140
0$
#145
b1000010100000100 !
1$
b110000000100000010000000110100001010000010 '
b1000000100000001100000000000000 &
#150
0$
#155
b101000001000 !
1$
1%
b110000000100000010000000111000010100000100 '
b10000001000000011000000000000000 &
#160
0$
#165
b1010000010000 !
1$
0%
b110000000100000010000000110000101000001000 '
b10000000110000000000000000 &
#170
0$
#175
b10100000100000 !
1$
b110000000100000010000000110001010000010000 '
b100000001100000000000000000 &
#180
0$
#185
b101000001000000 !
1$
b110000000100000010000000110010100000100000 '
b1000000011000000000000000000 &
#190
0$
#195
b1010000010000000 !
1$
b110000000100000010000000110101000001000000 '
b10000000110000000000000000000 &
#200
0$
#205
b1100000100000101 !
1$
b110000000100000010000000111010000010000000 '
b100000001100000000000000000000 &
#210
0$
#215
b1000001111 !
1$
b110000000100000010000000111100000100000101 '
b1000000011000000000000000000000 &
#220
0$
#225
b1000010000011011 !
1$
1%
b110000000100000010000000110000001000001111 '
b10000000110000000000000000000000 &
#230
0$
#235
b1000100000110011 !
1$
0%
b110000000100000010000000111000010000011011 '
b1100000000000000000000000 &
#240
0$
#245
b1001000001100011 !
1$
b110000000100000010000000111000100000110011 '
b11000000000000000000000000 &
#250
0$
#255
b1010000011000011 !
1$
b110000000100000010000000111001000001100011 '
b110000000000000000000000000 &
#260
0$
#265
b1100000110000011 !
1$
b110000000100000010000000111010000011000011 '
b1100000000000000000000000000 &
#270
0$
#275
b1100000011 !
1$
b110000000100000010000000111100000110000011 '
b11000000000000000000000000000 &
#280
0$
#285
b11000000110 !
1$
b110000000100000010000000110000001100000011 '
b110000000000000000000000000000 &
#290
0$
#295
b110000001100 !
1$
b110000000100000010000000110000011000000110 '
b1100000000000000000000000000000 &
#300
0$
#305
b1001100000011101 !
1$
1%
b110000000100000010000000110000110000001100 '
b11000000000000000000000000000000 &
#310
0$
#315
b11000000111010 !
1$
b110000000100000010000000111001100000011101 '
b10000000000000000000000000000000 &
#320
0$
#325
1$
b110000000100000010000000110011000000111010 '
b0 &
#330
b101000101000010011001000111111001100111100111100010000000011001100000000010010100011000100100000 #
0$
1"
#335
1$
#340
0$
#345
1$
#350
0$
#660
b10xxxxxxxxxxxxxxxxxxxxxxxxxxxxxxxxxxxxxxxxxxxxxxxxxxxxxxxxxxxxxxxxxxxxxxxxxxxxxxxxxxxxxxxxxxxxxx #
1"
